{  "teamTableStats" :  [{"name":"Coventry","teamId":17,"teamName":"Coventry","teamRegionName":"England","seasonId":0,"seasonName":null,"tournamentId":7,"isOpta":true,"tournamentRegionId":252,"tournamentRegionCode":"gb-eng","tournamentRegionName":"England","regionCode":null,"tournamentName":"Championship","rating":6.78,"ranking":1,"apps":34,"xG":67.636798683046052,"goalExcOwn":68,"totalShots":563,"xGDiff":0.36320131695394764,"xGPerShot":0.12013640973898056},{"name":"Southampton","teamId":18,"teamName":"Southampton","teamRegionName":"England","seasonId":0,"seasonName":null,"tournamentId":7,"isOpta":true,"tournamentRegionId":252,"tournamentRegionCode":"gb-eng","tournamentRegionName":"England","regionCode":null,"tournamentName":"Championship","rating":6.64,"ranking":2,"apps":34,"xG":61.177332244943962,"goalExcOwn":54,"totalShots":494,"xGDiff":-7.1773322449439618,"xGPerShot":0.12384075353227522},{"name":"Ipswich","teamId":165,"teamName":"Ipswich","teamRegionName":"England","seasonId":0,"seasonName":null,"tournamentId":7,"isOpta":true,"tournamentRegionId":252,"tournamentRegionCode":"gb-eng","tournamentRegionName":"England","regionCode":null,"tournamentName":"Championship","rating":6.65,"ranking":3,"apps":32,"xG":59.710664717609092,"goalExcOwn":51,"totalShots":492,"xGDiff":-8.7106647176090917,"xGPerShot":0.12136313966993718},{"name":"Sheff Utd","teamId":163,"teamName":"Sheffield United","teamRegionName":"England","seasonId":0,"seasonName":null,"tournamentId":7,"isOpta":true,"tournamentRegionId":252,"tournamentRegionCode":"gb-eng","tournamentRegionName":"England","regionCode":null,"tournamentName":"Championship","rating":6.63,"ranking":4,"apps":34,"xG":56.706631218913031,"goalExcOwn":47,"totalShots":454,"xGDiff":-9.7066312189130315,"xGPerShot":0.12490447405046923},{"name":"Birmingham","teamId":157,"teamName":"Birmingham","teamRegionName":"England","seasonId":0,"seasonName":null,"tournamentId":7,"isOpta":true,"tournamentRegionId":252,"tournamentRegionCode":"gb-eng","tournamentRegionName":"England","regionCode":null,"tournamentName":"Championship","rating":6.57,"ranking":5,"apps":34,"xG":55.978553050831316,"goalExcOwn":44,"totalShots":477,"xGDiff":-11.978553050831316,"xGPerShot":0.1173554571296254},{"name":"Watford","teamId":27,"teamName":"Watford","teamRegionName":"England","seasonId":0,"seasonName":null,"tournamentId":7,"isOpta":true,"tournamentRegionId":252,"tournamentRegionCode":"gb-eng","tournamentRegionName":"England","regionCode":null,"tournamentName":"Championship","rating":6.63,"ranking":6,"apps":35,"xG":51.657307431066975,"goalExcOwn":44,"totalShots":487,"xGDiff":-7.6573074310669753,"xGPerShot":0.10607249985845375},{"name":"Hull","teamId":214,"teamName":"Hull","teamRegionName":"England","seasonId":0,"seasonName":null,"tournamentId":7,"isOpta":true,"tournamentRegionId":252,"tournamentRegionCode":"gb-eng","tournamentRegionName":"England","regionCode":null,"tournamentName":"Championship","rating":6.67,"ranking":7,"apps":33,"xG":50.782777994030042,"goalExcOwn":53,"totalShots":368,"xGDiff":2.2172220059699583,"xGPerShot":0.13799667933160337},{"name":"Millwall","teamId":192,"teamName":"Millwall","teamRegionName":"England","seasonId":0,"seasonName":null,"tournamentId":7,"isOpta":true,"tournamentRegionId":252,"tournamentRegionCode":"gb-eng","tournamentRegionName":"England","regionCode":null,"tournamentName":"Championship","rating":6.66,"ranking":8,"apps":34,"xG":50.323417302271992,"goalExcOwn":41,"totalShots":434,"xGDiff":-9.3234173022719915,"xGPerShot":0.11595257442919814},{"name":"Norwich","teamId":168,"teamName":"Norwich","teamRegionName":"England","seasonId":0,"seasonName":null,"tournamentId":7,"isOpta":true,"tournamentRegionId":252,"tournamentRegionCode":"gb-eng","tournamentRegionName":"England","regionCode":null,"tournamentName":"Championship","rating":6.63,"ranking":9,"apps":34,"xG":50.15365188524,"goalExcOwn":43,"totalShots":415,"xGDiff":-7.1536518852400022,"xGPerShot":0.12085217321744579},{"name":"Wrexham","teamId":199,"teamName":"Wrexham","teamRegionName":"Wales","seasonId":0,"seasonName":null,"tournamentId":7,"isOpta":true,"tournamentRegionId":252,"tournamentRegionCode":"gb-eng","tournamentRegionName":"England","regionCode":null,"tournamentName":"Championship","rating":6.71,"ranking":10,"apps":34,"xG":49.290669303877976,"goalExcOwn":49,"totalShots":393,"xGDiff":-0.2906693038779764,"xGPerShot":0.125421550391547},{"name":"Middlesbrough","teamId":21,"teamName":"Middlesbrough","teamRegionName":"England","seasonId":0,"seasonName":null,"tournamentId":7,"isOpta":true,"tournamentRegionId":252,"tournamentRegionCode":"gb-eng","tournamentRegionName":"England","regionCode":null,"tournamentName":"Championship","rating":6.68,"ranking":11,"apps":34,"xG":48.358656054175839,"goalExcOwn":48,"totalShots":507,"xGDiff":-0.35865605417583879,"xGPerShot":0.095381964603897113},{"name":"Bristol City","teamId":182,"teamName":"Bristol City","teamRegionName":"England","seasonId":0,"seasonName":null,"tournamentId":7,"isOpta":true,"tournamentRegionId":252,"tournamentRegionCode":"gb-eng","tournamentRegionName":"England","regionCode":null,"tournamentName":"Championship","rating":6.66,"ranking":12,"apps":35,"xG":47.187425468483546,"goalExcOwn":47,"totalShots":445,"xGDiff":-0.18742546848354635,"xGPerShot":0.1060391583561428},{"name":"WBA","teamId":175,"teamName":"West Bromwich Albion","teamRegionName":"England","seasonId":0,"seasonName":null,"tournamentId":7,"isOpta":true,"tournamentRegionId":252,"tournamentRegionCode":"gb-eng","tournamentRegionName":"England","regionCode":null,"tournamentName":"Championship","rating":6.53,"ranking":13,"apps":34,"xG":46.078305467519996,"goalExcOwn":32,"totalShots":453,"xGDiff":-14.078305467519996,"xGPerShot":0.10171811361483443},{"name":"Blackburn","teamId":158,"teamName":"Blackburn","teamRegionName":"England","seasonId":0,"seasonName":null,"tournamentId":7,"isOpta":true,"tournamentRegionId":252,"tournamentRegionCode":"gb-eng","tournamentRegionName":"England","regionCode":null,"tournamentName":"Championship","rating":6.61,"ranking":14,"apps":34,"xG":46.03276035064998,"goalExcOwn":32,"totalShots":399,"xGDiff":-14.03276035064998,"xGPerShot":0.11537032669335835},{"name":"QPR","teamId":171,"teamName":"Queens Park Rangers","teamRegionName":"England","seasonId":0,"seasonName":null,"tournamentId":7,"isOpta":true,"tournamentRegionId":252,"tournamentRegionCode":"gb-eng","tournamentRegionName":"England","regionCode":null,"tournamentName":"Championship","rating":6.59,"ranking":15,"apps":34,"xG":45.216512094330007,"goalExcOwn":42,"totalShots":434,"xGDiff":-3.2165120943300067,"xGPerShot":0.10418551173808757},{"name":"Derby","teamId":20,"teamName":"Derby","teamRegionName":"England","seasonId":0,"seasonName":null,"tournamentId":7,"isOpta":true,"tournamentRegionId":252,"tournamentRegionCode":"gb-eng","tournamentRegionName":"England","regionCode":null,"tournamentName":"Championship","rating":6.61,"ranking":16,"apps":34,"xG":44.073381889999951,"goalExcOwn":46,"totalShots":345,"xGDiff":1.9266181100000495,"xGPerShot":0.12774893301449261},{"name":"Charlton","teamId":160,"teamName":"Charlton","teamRegionName":"England","seasonId":0,"seasonName":null,"tournamentId":7,"isOpta":true,"tournamentRegionId":252,"tournamentRegionCode":"gb-eng","tournamentRegionName":"England","regionCode":null,"tournamentName":"Championship","rating":6.58,"ranking":17,"apps":34,"xG":41.790061706218,"goalExcOwn":32,"totalShots":374,"xGDiff":-9.7900617062179975,"xGPerShot":0.1117381329043262},{"name":"Stoke","teamId":96,"teamName":"Stoke","teamRegionName":"England","seasonId":0,"seasonName":null,"tournamentId":7,"isOpta":true,"tournamentRegionId":252,"tournamentRegionCode":"gb-eng","tournamentRegionName":"England","regionCode":null,"tournamentName":"Championship","rating":6.62,"ranking":18,"apps":34,"xG":41.140230402951985,"goalExcOwn":36,"totalShots":384,"xGDiff":-5.1402304029519854,"xGPerShot":0.10713601667435413},{"name":"Swansea","teamId":259,"teamName":"Swansea","teamRegionName":"Wales","seasonId":0,"seasonName":null,"tournamentId":7,"isOpta":true,"tournamentRegionId":252,"tournamentRegionCode":"gb-eng","tournamentRegionName":"England","regionCode":null,"tournamentName":"Championship","rating":6.63,"ranking":19,"apps":34,"xG":40.429008515187995,"goalExcOwn":39,"totalShots":421,"xGDiff":-1.429008515187995,"xGPerShot":0.09603089908595723},{"name":"Leicester","teamId":14,"teamName":"Leicester","teamRegionName":"England","seasonId":0,"seasonName":null,"tournamentId":7,"isOpta":true,"tournamentRegionId":252,"tournamentRegionCode":"gb-eng","tournamentRegionName":"England","regionCode":null,"tournamentName":"Championship","rating":6.57,"ranking":20,"apps":34,"xG":40.304385310676217,"goalExcOwn":46,"totalShots":397,"xGDiff":5.6956146893237829,"xGPerShot":0.10152238113520458},{"name":"Portsmouth","teamId":169,"teamName":"Portsmouth","teamRegionName":"England","seasonId":0,"seasonName":null,"tournamentId":7,"isOpta":true,"tournamentRegionId":252,"tournamentRegionCode":"gb-eng","tournamentRegionName":"England","regionCode":null,"tournamentName":"Championship","rating":6.57,"ranking":21,"apps":33,"xG":40.286197387093978,"goalExcOwn":34,"totalShots":405,"xGDiff":-6.2861973870939778,"xGPerShot":0.0994720923138123},{"name":"Preston","teamId":181,"teamName":"Preston","teamRegionName":"England","seasonId":0,"seasonName":null,"tournamentId":7,"isOpta":true,"tournamentRegionId":252,"tournamentRegionCode":"gb-eng","tournamentRegionName":"England","regionCode":null,"tournamentName":"Championship","rating":6.64,"ranking":22,"apps":34,"xG":40.08870717557803,"goalExcOwn":40,"totalShots":367,"xGDiff":-0.088707175578029762,"xGPerShot":0.10923353453835975},{"name":"Oxford","teamId":197,"teamName":"Oxford","teamRegionName":"England","seasonId":0,"seasonName":null,"tournamentId":7,"isOpta":true,"tournamentRegionId":252,"tournamentRegionCode":"gb-eng","tournamentRegionName":"England","regionCode":null,"tournamentName":"Championship","rating":6.53,"ranking":23,"apps":34,"xG":35.901716058659673,"goalExcOwn":27,"totalShots":398,"xGDiff":-8.9017160586596731,"xGPerShot":0.090205316730300689},{"name":"Sheff Wed","teamId":25,"teamName":"Sheffield Wednesday","teamRegionName":"England","seasonId":0,"seasonName":null,"tournamentId":7,"isOpta":true,"tournamentRegionId":252,"tournamentRegionCode":"gb-eng","tournamentRegionName":"England","regionCode":null,"tournamentName":"Championship","rating":6.41,"ranking":24,"apps":34,"xG":28.759690942405339,"goalExcOwn":20,"totalShots":291,"xGDiff":-8.7596909424053386,"xGPerShot":0.098830553066685}],  "paging" : {   "currentPage" :  1, "totalPages" :  0, "resultsPerPage" :  0, "totalResults" :  0, "firstRecordIndex" :  0, "lastRecordIndex" :  0},  "statColumns" :  ["apps","xG","goalExcOwn","xGDiff","totalShots","xGPerShot"] } 
