{  "teamTableStats" :  [{"name":"Bayern","teamId":37,"teamName":"Bayern Munich","teamRegionName":"Germany","seasonId":0,"seasonName":null,"tournamentId":3,"isOpta":true,"tournamentRegionId":81,"tournamentRegionCode":"de","tournamentRegionName":"Germany","regionCode":"de","tournamentName":"Bundesliga","rating":7.01,"ranking":1,"apps":23,"shotsPerGame":19.130434782608695,"shotOnTargetPerGame":8.91304347826087,"dribbleWonPerGame":9.5217391304347831,"foulGivenPerGame":8.3478260869565215},{"name":"RBL","teamId":7614,"teamName":"RB Leipzig","teamRegionName":"Germany","seasonId":0,"seasonName":null,"tournamentId":3,"isOpta":true,"tournamentRegionId":81,"tournamentRegionCode":"de","tournamentRegionName":"Germany","regionCode":"de","tournamentName":"Bundesliga","rating":6.79,"ranking":2,"apps":23,"shotsPerGame":16.217391304347824,"shotOnTargetPerGame":5.6956521739130439,"dribbleWonPerGame":11.391304347826088,"foulGivenPerGame":10.347826086956522},{"name":"Stuttgart","teamId":41,"teamName":"VfB Stuttgart","teamRegionName":"Germany","seasonId":0,"seasonName":null,"tournamentId":3,"isOpta":true,"tournamentRegionId":81,"tournamentRegionCode":"de","tournamentRegionName":"Germany","regionCode":"de","tournamentName":"Bundesliga","rating":6.73,"ranking":3,"apps":23,"shotsPerGame":14.869565217391305,"shotOnTargetPerGame":5.8260869565217392,"dribbleWonPerGame":6.0869565217391308,"foulGivenPerGame":11.869565217391305},{"name":"Leverkusen","teamId":36,"teamName":"Bayer Leverkusen","teamRegionName":"Germany","seasonId":0,"seasonName":null,"tournamentId":3,"isOpta":true,"tournamentRegionId":81,"tournamentRegionCode":"de","tournamentRegionName":"Germany","regionCode":"de","tournamentName":"Bundesliga","rating":6.6899999999999995,"ranking":4,"apps":22,"shotsPerGame":13.772727272727273,"shotOnTargetPerGame":4.5454545454545459,"dribbleWonPerGame":7.0909090909090908,"foulGivenPerGame":11.0},{"name":"Hoffenheim","teamId":1211,"teamName":"Hoffenheim","teamRegionName":"Germany","seasonId":0,"seasonName":null,"tournamentId":3,"isOpta":true,"tournamentRegionId":81,"tournamentRegionCode":"de","tournamentRegionName":"Germany","regionCode":"de","tournamentName":"Bundesliga","rating":6.76,"ranking":5,"apps":23,"shotsPerGame":13.478260869565217,"shotOnTargetPerGame":5.0,"dribbleWonPerGame":5.6086956521739131,"foulGivenPerGame":9.1739130434782616},{"name":"Werder Bremen","teamId":42,"teamName":"Werder Bremen","teamRegionName":"Germany","seasonId":0,"seasonName":null,"tournamentId":3,"isOpta":true,"tournamentRegionId":81,"tournamentRegionCode":"de","tournamentRegionName":"Germany","regionCode":"de","tournamentName":"Bundesliga","rating":6.5,"ranking":6,"apps":23,"shotsPerGame":13.304347826086957,"shotOnTargetPerGame":4.0869565217391308,"dribbleWonPerGame":6.2173913043478262,"foulGivenPerGame":9.0434782608695645},{"name":"Hamburg","teamId":38,"teamName":"Hamburger SV","teamRegionName":"Germany","seasonId":0,"seasonName":null,"tournamentId":3,"isOpta":true,"tournamentRegionId":81,"tournamentRegionCode":"de","tournamentRegionName":"Germany","regionCode":"de","tournamentName":"Bundesliga","rating":6.5600000000000005,"ranking":7,"apps":22,"shotsPerGame":13.181818181818182,"shotOnTargetPerGame":4.8181818181818183,"dribbleWonPerGame":7.5,"foulGivenPerGame":12.545454545454545},{"name":"Borussia Dortmund","teamId":44,"teamName":"Borussia Dortmund","teamRegionName":"Germany","seasonId":0,"seasonName":null,"tournamentId":3,"isOpta":true,"tournamentRegionId":81,"tournamentRegionCode":"de","tournamentRegionName":"Germany","regionCode":"de","tournamentName":"Bundesliga","rating":6.8,"ranking":8,"apps":23,"shotsPerGame":13.130434782608695,"shotOnTargetPerGame":4.9130434782608692,"dribbleWonPerGame":8.08695652173913,"foulGivenPerGame":9.91304347826087},{"name":"FC Koln","teamId":282,"teamName":"FC Koln","teamRegionName":"Germany","seasonId":0,"seasonName":null,"tournamentId":3,"isOpta":true,"tournamentRegionId":81,"tournamentRegionCode":"de","tournamentRegionName":"Germany","regionCode":"de","tournamentName":"Bundesliga","rating":6.58,"ranking":9,"apps":23,"shotsPerGame":13.043478260869565,"shotOnTargetPerGame":4.4347826086956523,"dribbleWonPerGame":4.8695652173913047,"foulGivenPerGame":10.217391304347826},{"name":"Augsburg","teamId":1730,"teamName":"Augsburg","teamRegionName":"Germany","seasonId":0,"seasonName":null,"tournamentId":3,"isOpta":true,"tournamentRegionId":81,"tournamentRegionCode":"de","tournamentRegionName":"Germany","regionCode":"de","tournamentName":"Bundesliga","rating":6.51,"ranking":10,"apps":23,"shotsPerGame":12.826086956521738,"shotOnTargetPerGame":4.3913043478260869,"dribbleWonPerGame":6.8260869565217392,"foulGivenPerGame":11.739130434782609},{"name":"Union Berlin","teamId":796,"teamName":"Union Berlin","teamRegionName":"Germany","seasonId":0,"seasonName":null,"tournamentId":3,"isOpta":true,"tournamentRegionId":81,"tournamentRegionCode":"de","tournamentRegionName":"Germany","regionCode":"de","tournamentName":"Bundesliga","rating":6.55,"ranking":11,"apps":23,"shotsPerGame":12.739130434782609,"shotOnTargetPerGame":3.652173913043478,"dribbleWonPerGame":4.7826086956521738,"foulGivenPerGame":10.260869565217391},{"name":"Freiburg","teamId":50,"teamName":"Freiburg","teamRegionName":"Germany","seasonId":0,"seasonName":null,"tournamentId":3,"isOpta":true,"tournamentRegionId":81,"tournamentRegionCode":"de","tournamentRegionName":"Germany","regionCode":"de","tournamentName":"Bundesliga","rating":6.5600000000000005,"ranking":12,"apps":23,"shotsPerGame":12.434782608695652,"shotOnTargetPerGame":4.0869565217391308,"dribbleWonPerGame":5.6086956521739131,"foulGivenPerGame":11.782608695652174},{"name":"FC Heidenheim","teamId":4852,"teamName":"FC Heidenheim","teamRegionName":"Germany","seasonId":0,"seasonName":null,"tournamentId":3,"isOpta":true,"tournamentRegionId":81,"tournamentRegionCode":"de","tournamentRegionName":"Germany","regionCode":"de","tournamentName":"Bundesliga","rating":6.39,"ranking":13,"apps":23,"shotsPerGame":11.913043478260869,"shotOnTargetPerGame":3.6086956521739131,"dribbleWonPerGame":5.3913043478260869,"foulGivenPerGame":9.91304347826087},{"name":"Wolfsburg","teamId":33,"teamName":"Wolfsburg","teamRegionName":"Germany","seasonId":0,"seasonName":null,"tournamentId":3,"isOpta":true,"tournamentRegionId":81,"tournamentRegionCode":"de","tournamentRegionName":"Germany","regionCode":"de","tournamentName":"Bundesliga","rating":6.53,"ranking":14,"apps":23,"shotsPerGame":11.608695652173912,"shotOnTargetPerGame":3.9565217391304346,"dribbleWonPerGame":4.7826086956521738,"foulGivenPerGame":9.3913043478260878},{"name":"Eintracht Frankfurt","teamId":45,"teamName":"Eintracht Frankfurt","teamRegionName":"Germany","seasonId":0,"seasonName":null,"tournamentId":3,"isOpta":true,"tournamentRegionId":81,"tournamentRegionCode":"de","tournamentRegionName":"Germany","regionCode":"de","tournamentName":"Bundesliga","rating":6.55,"ranking":15,"apps":23,"shotsPerGame":11.478260869565217,"shotOnTargetPerGame":4.3913043478260869,"dribbleWonPerGame":6.4347826086956523,"foulGivenPerGame":9.08695652173913},{"name":"Mainz","teamId":219,"teamName":"Mainz 05","teamRegionName":"Germany","seasonId":0,"seasonName":null,"tournamentId":3,"isOpta":true,"tournamentRegionId":81,"tournamentRegionCode":"de","tournamentRegionName":"Germany","regionCode":"de","tournamentName":"Bundesliga","rating":6.5600000000000005,"ranking":16,"apps":23,"shotsPerGame":11.391304347826088,"shotOnTargetPerGame":3.6086956521739131,"dribbleWonPerGame":5.7391304347826084,"foulGivenPerGame":9.695652173913043},{"name":"Borussia M.Gladbach","teamId":134,"teamName":"Borussia M.Gladbach","teamRegionName":"Germany","seasonId":0,"seasonName":null,"tournamentId":3,"isOpta":true,"tournamentRegionId":81,"tournamentRegionCode":"de","tournamentRegionName":"Germany","regionCode":"de","tournamentName":"Bundesliga","rating":6.5600000000000005,"ranking":17,"apps":23,"shotsPerGame":11.260869565217391,"shotOnTargetPerGame":4.0,"dribbleWonPerGame":5.1304347826086953,"foulGivenPerGame":10.304347826086957},{"name":"St. Pauli","teamId":283,"teamName":"St. Pauli","teamRegionName":"Germany","seasonId":0,"seasonName":null,"tournamentId":3,"isOpta":true,"tournamentRegionId":81,"tournamentRegionCode":"de","tournamentRegionName":"Germany","regionCode":"de","tournamentName":"Bundesliga","rating":6.48,"ranking":18,"apps":23,"shotsPerGame":10.347826086956522,"shotOnTargetPerGame":3.5652173913043477,"dribbleWonPerGame":4.7826086956521738,"foulGivenPerGame":9.4782608695652169}],  "paging" : {   "currentPage" :  1, "totalPages" :  0, "resultsPerPage" :  0, "totalResults" :  0, "firstRecordIndex" :  0, "lastRecordIndex" :  0},  "statColumns" :  ["apps","shotsPerGame","shotOnTargetPerGame","dribbleWonPerGame","foulGivenPerGame"] } 
